[1,0,0,[["cc.JsonAsset",["_name","json"],1]],[[0,0,1,3]],[[0,"level",{"1":{"ID":"《------------爬塔玩法-------------》"},"2":{},"jdAwardArr":[{"ID":1,"dropArr":[[116,2],[1,2000],[2,200],[3,200],[117,2],[53,2],[2,200],[1,5000],[118,2],[2,300],[128,1]]},{"ID":2,"dropArr":[[116,2],[1,2000],[2,200],[3,200],[117,2],[53,2],[2,200],[1,5000],[118,2],[2,300],[128,1]]}],"fpArr":[{"ID":1,"intro":"必定包含:史诗武将X1","dropitem":[[101,1,1],[102,2,2],[104,1,3]]},{"ID":2,"intro":"必定包含:史诗武将X1","dropitem":[[105,1,1],[103,2,2],[104,1,3]]},{"ID":3,"intro":"必定包含:史诗武将X1","dropitem":[[109,1,1],[113,2,2],[104,1,3]]},{"ID":4,"intro":"必定包含:史诗武将X1","dropitem":[[114,1,1],[116,2,2],[108,1,3]]},{"ID":5,"intro":"必定包含:史诗武将X1","dropitem":[[101,1,1],[120,2,2],[108,1,3]]},{"ID":6,"intro":"必定包含:史诗武将X1","dropitem":[[105,1,1],[125,2,2],[108,1,3]]},{"ID":7,"intro":"必定包含:史诗武将X1","dropitem":[[109,1,1],[129,2,2],[112,1,3]]},{"ID":8,"intro":"必定包含:史诗武将X1","dropitem":[[114,1,1],[102,2,2],[112,1,3]]},{"ID":9,"intro":"必定包含:史诗武将X1","dropitem":[[101,1,1],[103,2,2],[112,1,3]]},{"ID":10,"intro":"必定包含:史诗武将X1","dropitem":[[105,1,1],[113,2,2],[115,1,3]]},{"ID":11,"intro":"必定包含:史诗武将X1","dropitem":[[109,1,1],[116,2,2],[115,1,3]]},{"ID":12,"intro":"必定包含:史诗武将X1","dropitem":[[114,1,1],[120,2,2],[115,1,3]]},{"ID":13,"intro":"必定包含:史诗武将X1","dropitem":[[101,1,1],[125,2,2],[117,1,3]]},{"ID":14,"intro":"必定包含:史诗武将X1","dropitem":[[105,1,1],[129,2,2],[117,1,3]]},{"ID":15,"intro":"必定包含:史诗武将X1","dropitem":[[109,1,1],[102,2,2],[117,1,3]]},{"ID":16,"intro":"必定包含:史诗武将X1","dropitem":[[114,1,1],[103,2,2],[118,1,3]]},{"ID":17,"intro":"必定包含:史诗武将X1","dropitem":[[101,1,1],[113,2,2],[118,1,3]]},{"ID":18,"intro":"必定包含:史诗武将X1","dropitem":[[105,1,1],[116,2,2],[118,1,3]]},{"ID":19,"intro":"必定包含:史诗武将X1","dropitem":[[109,1,1],[120,2,2],[122,1,3]]},{"ID":20,"intro":"必定包含:史诗武将X1","dropitem":[[114,1,1],[125,2,2],[122,1,3]]},{"ID":21,"intro":"必定包含:史诗武将X1","dropitem":[[101,1,1],[129,2,2],[122,1,3]]},{"ID":22,"intro":"必定包含:史诗武将X1","dropitem":[[105,1,1],[102,2,2],[124,1,3]]},{"ID":23,"intro":"必定包含:史诗武将X1","dropitem":[[109,1,1],[103,2,2],[124,1,3]]},{"ID":24,"intro":"必定包含:史诗武将X1","dropitem":[[114,1,1],[113,2,2],[124,1,3]]},{"ID":25,"intro":"必定包含:优秀武将X3","dropitem":[[2,10,1],[101,2,1],[102,3,2]]},{"ID":26,"intro":"必定包含:优秀武将X3","dropitem":[[2,10,1],[105,2,1],[102,3,2]]},{"ID":27,"intro":"必定包含:优秀武将X3","dropitem":[[2,10,1],[109,2,1],[102,3,2]]},{"ID":28,"intro":"必定包含:优秀武将X3","dropitem":[[2,10,1],[114,2,1],[103,3,2]]},{"ID":29,"intro":"必定包含:优秀武将X3","dropitem":[[2,10,1],[101,2,1],[103,3,2]]},{"ID":30,"intro":"必定包含:优秀武将X3","dropitem":[[2,10,1],[105,2,1],[103,3,2]]},{"ID":31,"intro":"必定包含:优秀武将X3","dropitem":[[2,10,1],[109,2,1],[113,3,2]]},{"ID":32,"intro":"必定包含:优秀武将X3","dropitem":[[2,10,1],[114,2,1],[113,3,2]]},{"ID":33,"intro":"必定包含:优秀武将X3","dropitem":[[2,10,1],[101,2,1],[113,3,2]]},{"ID":34,"intro":"必定包含:优秀武将X3","dropitem":[[2,10,1],[105,2,1],[116,3,2]]},{"ID":35,"intro":"必定包含:优秀武将X3","dropitem":[[2,10,1],[109,2,1],[116,3,2]]},{"ID":36,"intro":"必定包含:优秀武将X3","dropitem":[[2,10,1],[114,2,1],[116,3,2]]},{"ID":37,"intro":"必定包含:优秀武将X3","dropitem":[[2,10,1],[101,2,1],[120,3,2]]},{"ID":38,"intro":"必定包含:优秀武将X3","dropitem":[[2,10,1],[105,2,1],[120,3,2]]},{"ID":39,"intro":"必定包含:优秀武将X3","dropitem":[[2,10,1],[109,2,1],[120,3,2]]},{"ID":40,"intro":"必定包含:优秀武将X3","dropitem":[[2,10,1],[114,2,1],[125,3,2]]},{"ID":41,"intro":"必定包含:优秀武将X3","dropitem":[[2,10,1],[101,2,1],[125,3,2]]},{"ID":42,"intro":"必定包含:优秀武将X3","dropitem":[[2,10,1],[105,2,1],[125,3,2]]},{"ID":43,"intro":"必定包含:优秀武将X3","dropitem":[[2,10,1],[109,2,1],[129,3,2]]},{"ID":44,"intro":"必定包含:优秀武将X3","dropitem":[[2,10,1],[114,2,1],[129,3,2]]},{"ID":45,"intro":"必定包含:优秀武将X3","dropitem":[[2,10,1],[101,2,1],[129,3,2]]},{"ID":46,"intro":"必定包含:橙色武器X1","dropitem":[[6,10,1],[102,2,2],[0,105,3,1]]},{"ID":47,"intro":"必定包含:橙色武器X1","dropitem":[[6,10,1],[103,2,2],[0,105,3,1]]},{"ID":48,"intro":"必定包含:橙色武器X1","dropitem":[[6,10,1],[113,2,2],[0,105,3,1]]},{"ID":49,"intro":"必定包含:橙色武器X1","dropitem":[[1,300,1],[116,2,2],[0,106,3,1]]},{"ID":50,"intro":"必定包含:橙色武器X1","dropitem":[[1,300,1],[120,2,2],[0,106,3,1]]},{"ID":51,"intro":"必定包含:橙色武器X1","dropitem":[[1,300,1],[125,2,2],[0,106,3,1]]},{"ID":52,"intro":"必定包含:橙色武器X1","dropitem":[[1,300,1],[129,2,2],[0,107,3,1]]},{"ID":53,"intro":"必定包含:橙色武器X1","dropitem":[[1,300,1],[102,2,2],[0,107,3,1]]},{"ID":54,"intro":"必定包含:橙色武器X1","dropitem":[[1,300,1],[103,2,2],[0,107,3,1]]},{"ID":55,"intro":"必定包含:橙色武器X1","dropitem":[[105,1,1],[2,100,2],[0,202,3,1]]},{"ID":56,"intro":"必定包含:橙色武器X1","dropitem":[[109,1,1],[2,100,2],[0,202,3,1]]},{"ID":57,"intro":"必定包含:橙色武器X1","dropitem":[[114,1,1],[2,100,2],[0,202,3,1]]},{"ID":58,"intro":"必定包含:橙色武器X1","dropitem":[[101,1,1],[2,100,2],[0,302,3,1]]},{"ID":59,"intro":"必定包含:橙色武器X1","dropitem":[[105,1,1],[2,100,2],[0,302,3,1]]},{"ID":60,"intro":"必定包含:橙色武器X1","dropitem":[[109,1,1],[2,100,2],[0,302,3,1]]},{"ID":61,"intro":"必定包含:橙色武器X1","dropitem":[[109,1,1],[2,100,2],[0,402,3,1]]},{"ID":62,"intro":"必定包含:橙色武器X1","dropitem":[[114,1,1],[2,100,2],[0,402,3,1]]},{"ID":63,"intro":"必定包含:橙色武器X1","dropitem":[[101,1,1],[2,100,2],[0,402,3,1]]},{"ID":64,"intro":"必定包含:200妖鸡玉","dropitem":[[101,1,1],[102,2,2],[2,200,3]]},{"ID":65,"intro":"必定包含:200妖鸡玉","dropitem":[[105,1,1],[103,2,2],[2,200,3]]},{"ID":66,"intro":"必定包含:200妖鸡玉","dropitem":[[109,1,1],[113,2,2],[2,200,3]]},{"ID":67,"intro":"必定包含:200妖鸡玉","dropitem":[[114,1,1],[116,2,2],[2,200,3]]},{"ID":68,"intro":"必定包含:200妖鸡玉","dropitem":[[101,1,1],[120,2,2],[2,200,3]]},{"ID":69,"intro":"必定包含:200妖鸡玉","dropitem":[[105,1,1],[125,2,2],[2,200,3]]},{"ID":70,"intro":"必定包含:200妖鸡玉","dropitem":[[109,1,1],[129,2,2],[2,200,3]]},{"ID":71,"intro":"必定包含:200妖鸡玉","dropitem":[[114,1,1],[102,2,2],[2,200,3]]},{"ID":72,"intro":"必定包含:200妖鸡玉","dropitem":[[101,1,1],[103,2,2],[2,200,3]]},{"ID":73,"intro":"必定包含:200妖鸡玉","dropitem":[[105,1,1],[113,2,2],[2,200,3]]},{"ID":74,"intro":"必定包含:200妖鸡玉","dropitem":[[109,1,1],[116,2,2],[2,200,3]]},{"ID":75,"intro":"必定包含:200妖鸡玉","dropitem":[[114,1,1],[120,2,2],[2,200,3]]},{"ID":76,"intro":"必定包含:200妖鸡玉","dropitem":[[101,1,1],[125,2,2],[2,200,3]]},{"ID":77,"intro":"必定包含:200妖鸡玉","dropitem":[[105,1,1],[129,2,2],[2,200,3]]},{"ID":78,"intro":"必定包含:200妖鸡玉","dropitem":[[109,1,1],[102,2,2],[2,200,3]]},{"ID":79,"intro":"必定包含:200妖鸡玉","dropitem":[[114,1,1],[103,2,2],[2,200,3]]},{"ID":80,"intro":"必定包含:200妖鸡玉","dropitem":[[101,1,1],[113,2,2],[2,200,3]]},{"ID":81,"intro":"必定包含:200妖鸡玉","dropitem":[[105,1,1],[116,2,2],[2,200,3]]},{"ID":82,"intro":"必定包含:200妖鸡玉","dropitem":[[109,1,1],[120,2,2],[2,200,3]]},{"ID":83,"intro":"必定包含:200妖鸡玉","dropitem":[[114,1,1],[125,2,2],[2,200,3]]},{"ID":84,"intro":"必定包含:200妖鸡玉","dropitem":[[101,1,1],[129,2,2],[2,200,3]]},{"ID":85,"intro":"必定包含:200妖鸡玉","dropitem":[[105,1,1],[102,2,2],[2,200,3]]},{"ID":86,"intro":"必定包含:200妖鸡玉","dropitem":[[109,1,1],[103,2,2],[2,200,3]]},{"ID":87,"intro":"必定包含:200妖鸡玉","dropitem":[[114,1,1],[113,2,2],[2,200,3]]},{"ID":88,"intro":"必定包含:50体力","dropitem":[[0,108,1,2],[102,2,2],[6,50,3]]},{"ID":89,"intro":"必定包含:50体力","dropitem":[[0,109,1,2],[102,2,2],[6,50,3]]},{"ID":90,"intro":"必定包含:50体力","dropitem":[[0,110,1,2],[102,2,2],[6,50,3]]},{"ID":91,"intro":"必定包含:50体力","dropitem":[[0,203,1,2],[103,2,2],[6,50,3]]},{"ID":92,"intro":"必定包含:50体力","dropitem":[[0,204,1,2],[103,2,2],[6,50,3]]},{"ID":93,"intro":"必定包含:50体力","dropitem":[[0,205,1,2],[103,2,2],[6,50,3]]},{"ID":94,"intro":"必定包含:50体力","dropitem":[[0,303,1,2],[113,2,2],[6,50,3]]},{"ID":95,"intro":"必定包含:50体力","dropitem":[[0,304,1,2],[113,2,2],[6,50,3]]},{"ID":96,"intro":"必定包含:50体力","dropitem":[[0,305,1,2],[113,2,2],[6,50,3]]},{"ID":97,"intro":"必定包含:50体力","dropitem":[[0,403,1,2],[116,2,2],[6,50,3]]},{"ID":98,"intro":"必定包含:50体力","dropitem":[[0,404,1,2],[116,2,2],[6,50,3]]},{"ID":99,"intro":"必定包含:50体力","dropitem":[[0,405,1,2],[116,2,2],[6,50,3]]},{"ID":100,"intro":"必定包含:50体力","dropitem":[[0,108,1,2],[120,2,2],[6,50,3]]},{"ID":101,"intro":"必定包含:50体力","dropitem":[[0,109,1,2],[120,2,2],[6,50,3]]},{"ID":102,"intro":"必定包含:50体力","dropitem":[[0,110,1,2],[120,2,2],[6,50,3]]},{"ID":103,"intro":"必定包含:50体力","dropitem":[[0,203,1,2],[125,2,2],[6,50,3]]},{"ID":104,"intro":"必定包含:50体力","dropitem":[[0,204,1,2],[125,2,2],[6,50,3]]},{"ID":105,"intro":"必定包含:50体力","dropitem":[[0,205,1,2],[125,2,2],[6,50,3]]},{"ID":106,"intro":"必定包含:50体力","dropitem":[[0,303,1,2],[129,2,2],[6,50,3]]},{"ID":107,"intro":"必定包含:50体力","dropitem":[[0,304,1,2],[129,2,2],[6,50,3]]},{"ID":108,"intro":"必定包含:50体力","dropitem":[[0,305,1,2],[129,2,2],[6,50,3]]},{"ID":109,"intro":"必定包含:50体力","dropitem":[[0,403,1,2],[102,2,2],[6,50,3]]},{"ID":110,"intro":"必定包含:50体力","dropitem":[[0,404,1,2],[103,2,2],[6,50,3]]},{"ID":111,"intro":"必定包含:50体力","dropitem":[[0,405,1,2],[116,2,2],[6,50,3]]}],"activeLevel":[{"ID":1,"towerID":401,"tjzdl":1000,"awardID":10001,"lvArr":[[[4,10,3],[8,10,3.1],[2,10,3.2],[1,10,10],[7,10,10.1],[2,10,10.2],[9,10,18],[4,10,18.1],[1,10,22],[2,10,22.1]],[[5,10,3],[6,10,3.1],[6,10,3.2],[7,10,10],[1,10,10.1],[2,10,10.2],[9,10,18],[4,10,18.1],[7,10,22],[2,10,22.1]]]},{"ID":2,"towerID":402,"tjzdl":1500,"awardID":10002,"lvArr":[[[6,11,3],[2,11,3.1],[2,11,3.2],[7,11,10],[1,11,10.1],[9,11,10.2],[8,11,18],[4,11,18.1],[1,11,22],[2,11,22.1]],[[6,11,3],[6,11,3.1],[6,11,3.2],[8,11,10],[1,11,10.1],[2,11,10.2],[9,11,18],[4,11,18.1],[7,11,22],[2,11,22.1]]]},{"ID":3,"towerID":403,"tjzdl":2000,"awardID":10003,"lvArr":[[[8,12,3],[6,12,3.1],[10,12,3.2],[7,12,10],[1,12,10.1],[2,12,10.2],[8,12,18],[4,12,18.1],[4,12,22],[7,12,22.1]],[[9,12,3],[2,12,3.1],[2,12,3.2],[6,12,10],[4,12,10.1],[4,12,10.2],[5,12,18],[2,12,18.1],[10,12,22],[9,12,22.1]]]},{"ID":4,"towerID":404,"tjzdl":2500,"awardID":10004,"lvArr":[[[6,13,3],[7,13,3.1],[2,13,3.2],[9,13,10],[8,13,10.1],[2,13,10.2],[2,13,18],[6,13,18.1],[4,13,22],[4,13,22.1]],[[9,13,3],[2,13,3.1],[2,13,3.2],[6,13,10],[4,13,10.1],[4,13,10.2],[5,13,18],[2,13,18.1],[10,13,22],[9,13,22.1]]]},{"ID":5,"towerID":405,"tjzdl":3000,"awardID":10005,"lvArr":[[[8,14,3],[2,14,3.1],[1,14,3.2],[7,14,10],[2,14,10.1],[6,14,10.2],[8,14,18],[6,14,18.1],[1,14,22],[6,14,22.1]],[[6,14,3],[7,14,3.1],[2,14,3.2],[9,14,10],[8,14,10.1],[2,14,10.2],[2,14,18],[6,14,18.1],[4,14,22],[4,14,22.1]],[[9,14,3],[2,14,3.5],[2,14,4],[11,14,4.5],[4,14,5],[4,14,5.5],[5,14,6],[2,14,6.5],[11,14,7],[9,14,8]],[[6,14,0.5],[8,14,1],[2,14,1.5],[9,14,2],[5014,20,2.5]]]},{"ID":6,"towerID":406,"tjzdl":1000,"awardID":10006,"lvArr":[[[7,15,3],[16,15,3.1],[11,15,3.2],[8,15,10],[4,15,10.1],[9,15,10.2],[7,15,18],[16,15,18.1],[1,15,22],[1,15,22.1]],[[6,15,3],[6,15,3.1],[17,15,3.2],[8,15,10],[10,15,10.1],[11,15,10.2],[7,15,18],[17,15,18.1],[2,15,22],[4,15,22.1]]]},{"ID":7,"towerID":407,"tjzdl":1000,"awardID":10007,"lvArr":[[[9,16,3],[2,16,3.1],[10,16,3.2],[8,16,10],[4,16,10.1],[9,16,10.2],[7,16,18],[4,16,18.1],[11,16,22],[1,16,22.1]],[[6,16,3],[4,16,3.1],[17,16,3.2],[8,16,10],[10,16,10.1],[7,16,10.2],[17,16,18],[8,16,18.1],[2,16,22],[4,12,22.1]]]},{"ID":8,"towerID":408,"tjzdl":1000,"awardID":10008,"lvArr":[[[7,17,3],[16,17,3.1],[11,17,3.2],[8,17,10],[4,17,10.1],[9,17,10.2],[7,17,18],[16,17,18.1],[1,17,22],[1,17,22.1]],[[6,17,3],[6,17,3.1],[17,17,3.2],[8,17,10],[10,17,10.1],[11,17,10.2],[7,17,18],[17,17,18.1],[2,17,22],[4,13,22.1]]]},{"ID":9,"towerID":409,"tjzdl":1000,"awardID":10009,"lvArr":[[[9,18,3],[2,18,3.1],[10,18,3.2],[8,18,10],[4,18,10.1],[9,18,10.2],[7,18,18],[4,18,18.1],[11,18,22],[1,18,22.1]],[[6,18,3],[4,18,3.1],[17,18,3.2],[8,18,10],[10,18,10.1],[7,18,10.2],[17,18,18],[8,18,18.1],[2,18,22],[4,14,22.1]]]},{"ID":10,"towerID":410,"tjzdl":1000,"awardID":10010,"lvArr":[[[5,19,3],[4,19,3.1],[8,19,3.2],[10,19,10],[17,19,10.1],[9,19,10.2],[11,19,18],[5,19,18.1],[2,19,22],[1,19,22.1]],[[9,19,3],[2,19,3.1],[10,19,3.2],[8,19,10],[4,19,10.1],[9,19,10.2],[7,19,18],[4,19,18.1],[11,19,22],[1,19,22.1]],[[6,19,3],[4,19,3.5],[17,19,4],[8,19,4.5],[10,19,5],[7,19,5.5],[17,19,6],[8,19,6.5],[2,19,7],[4,19,8]],[[19,19,0.5],[11,19,1],[13,19,1.5],[13,19,2],[5006,25,2.5],[13,19,3],[10,19,3.5],[17,19,4],[10,19,4.5],[10,19,5]]]},{"ID":11,"towerID":501,"tjzdl":1000,"awardID":10011,"lvArr":[[[6,20,3],[3,20,3.1],[10,20,3.2],[8,20,10],[4,20,10.1],[9,20,10.2],[7,20,18],[5,20,18.1],[3,20,22],[1,20,22.1]],[[4,20,3],[5,20,3.1],[4,20,3.2],[7,20,10],[10,20,10.1],[8,20,10.2],[7,20,18],[7,20,18.1],[2,20,22],[4,16,22.1]]]},{"ID":12,"towerID":502,"tjzdl":1000,"awardID":10012,"lvArr":[[[8,21,3],[1,21,3.1],[1,21,3.2],[5,21,10],[2,21,10.1],[2,21,10.2],[8,21,18],[9,21,18.1],[1,21,22],[7,21,22.1]],[[10,21,3],[1,21,3.1],[9,21,3.2],[4,21,10],[6,21,10.1],[4,21,10.2],[8,21,18],[2,21,18.1],[2,21,22],[10,17,22.1]]]},{"ID":13,"towerID":503,"tjzdl":1000,"awardID":10013,"lvArr":[[[6,22,3],[2,22,3.1],[10,22,3.2],[8,22,10],[4,22,10.1],[5,22,10.2],[11,22,18],[10,22,18.1],[4,22,22],[3,22,22.1]],[[5,22,3],[3,22,3.1],[7,22,3.2],[6,22,10],[11,22,10.1],[9,22,10.2],[8,22,18],[4,22,18.1],[1,22,22],[10,18,22.1]]]},{"ID":14,"towerID":504,"tjzdl":1000,"awardID":10014,"lvArr":[[[8,23,3],[7,23,3.1],[5,23,3.2],[4,23,10],[3,23,10.1],[10,23,10.2],[5,23,18],[3,23,18.1],[1,23,22],[9,23,22.1]],[[5,23,3],[3,23,3.1],[7,23,3.2],[5,23,10],[7,23,10.1],[9,23,10.2],[11,23,18],[10,23,18.1],[4,23,22],[3,19,22.1]]]},{"ID":15,"towerID":505,"tjzdl":1000,"awardID":10015,"lvArr":[[[8,24,3],[2,24,3.1],[1,24,3.2],[7,24,10],[2,24,10.1],[6,24,10.2],[8,24,18],[6,24,18.1],[12,24,22],[2,24,22.1]],[[6,24,3],[7,24,3.1],[2,24,3.2],[9,24,10],[8,24,10.1],[2,24,10.2],[2,24,18],[6,24,18.1],[2,24,22],[2,24,22.1]],[[9,24,3],[2,24,3.5],[2,24,4],[11,24,4.5],[4,24,5],[4,24,5.5],[5,24,6],[2,24,6.5],[11,24,7],[9,24,8]],[[6,24,0.5],[8,24,1],[2,24,1.5],[9,24,2],[5021,30,2.5]]]},{"ID":16,"towerID":506,"tjzdl":1000,"awardID":10016,"lvArr":[[[3,25,3],[2,25,3.1],[10,25,3.2],[9,25,10],[7,25,10.1],[11,25,10.2],[10,25,18],[9,25,18.1],[3,25,22],[1,25,22.1]],[[9,25,3],[1,25,3.1],[4,25,3.2],[8,25,10],[9,25,10.1],[10,25,10.2],[7,25,18],[11,25,18.1],[2,25,22],[4,21,22.1]]]},{"ID":17,"towerID":507,"tjzdl":1000,"awardID":10017,"lvArr":[[[5,26,3],[2,26,3.1],[6,26,3.2],[10,26,10],[9,26,10.1],[11,26,10.2],[6,26,18],[5,26,18.1],[2,26,22],[1,26,22.1]],[[7,26,3],[6,26,3.1],[4,26,3.2],[8,26,10],[10,26,10.1],[5,26,10.2],[7,26,18],[11,26,18.1],[2,26,22],[4,22,22.1]]]},{"ID":18,"towerID":508,"tjzdl":1000,"awardID":10018,"lvArr":[[[6,27,3],[3,27,8],[10,27,10],[8,27,15],[4,27,15],[9,27,20],[7,27,20],[5,27,25],[3,27,25],[1,27,28]],[[4,27,4],[5,27,7],[4,27,12],[7,27,12],[10,27,17],[8,27,17],[7,27,22],[7,27,22],[2,27,22],[4,23,22]]]},{"ID":19,"towerID":509,"tjzdl":1000,"awardID":10019,"lvArr":[[[7,28,3],[2,28,3.1],[11,28,3.2],[8,28,10],[10,28,10.1],[8,28,10.2],[7,28,18],[4,28,18.1],[1,28,22],[1,28,22.1]],[[6,28,3],[5,28,3.1],[4,28,3.2],[8,28,10],[10,28,10.1],[6,28,10.2],[7,28,18],[11,28,18.1],[2,28,22],[4,28,22.1]]]},{"ID":20,"towerID":510,"tjzdl":1000,"awardID":10020,"lvArr":[[[8,29,3],[2,29,3.1],[1,29,3.2],[7,29,10],[2,29,10.1],[6,29,10.2],[8,29,18],[6,29,18.1],[12,29,22],[2,29,22.1]],[[6,29,3],[7,29,3.1],[2,29,3.2],[9,29,10],[8,29,10.1],[2,29,10.2],[2,29,18],[6,29,18.1],[2,29,22],[2,29,22.1]],[[12,29,3],[2,29,3.5],[2,29,4],[17,29,4.5],[4,29,5],[12,29,5.5],[15,29,6],[2,29,6.5],[17,29,7],[9,29,8]],[[9,29,0.5],[2,29,1],[2,29,1.5],[17,29,2],[5019,35,2.5],[4,29,3],[15,29,3.5],[2,29,4],[17,29,4.5],[9,29,5]]]},{"ID":21,"towerID":601,"tjzdl":1000,"awardID":10021,"lvArr":[[[8,30,3],[2,30,3.1],[1,30,3.2],[7,30,10],[2,30,10.1],[6,30,10.2],[8,30,18],[6,30,18.1],[12,30,22],[2,30,22.1]],[[6,30,3],[7,30,3.1],[2,30,3.2],[9,30,10],[8,30,10.1],[2,30,10.2],[2,30,18],[6,30,18.1],[2,30,22],[2,30,22.1]]]},{"ID":22,"towerID":602,"tjzdl":1000,"awardID":10022,"lvArr":[[[6,30,3],[3,30,3.1],[10,30,3.2],[8,30,10],[4,30,10.1],[9,30,10.2],[7,30,18],[5,30,18.1],[3,30,22],[1,30,22.1]],[[4,30,3],[5,30,3.1],[4,30,3.2],[7,30,10],[10,30,10.1],[8,30,10.2],[7,30,18],[7,30,18.1],[2,30,22],[4,30,22.1]]]},{"ID":23,"towerID":603,"tjzdl":1000,"awardID":10023,"lvArr":[[[6,32,3],[2,32,8],[10,32,10],[8,32,15],[4,32,15],[5,32,20],[11,32,20],[10,32,25],[4,32,25],[3,32,28]],[[5,32,4],[3,32,7],[7,32,12],[6,32,12],[11,32,17],[9,32,17],[8,32,22],[4,32,22],[1,32,22],[10,28,22]]]},{"ID":24,"towerID":604,"tjzdl":1000,"awardID":10024,"lvArr":[[[8,31,3],[1,31,3.1],[1,31,3.2],[5,31,10],[2,31,10.1],[2,31,10.2],[8,31,18],[9,31,18.1],[1,31,22],[7,31,22.1]],[[10,31,3],[1,31,3.1],[9,31,3.2],[4,31,10],[6,31,10.1],[4,31,10.2],[8,31,18],[2,31,18.1],[2,31,22],[10,31,22.1]]]},{"ID":25,"towerID":605,"tjzdl":1000,"awardID":10025,"lvArr":[[[5,33,3],[4,33,3.1],[8,33,3.2],[10,33,10],[4,33,10.1],[9,33,10.2],[6,33,18],[5,33,18.1],[2,33,22],[1,33,22.1]],[[3,33,3],[6,33,3.1],[4,33,3.2],[8,33,10],[10,33,10.1],[11,33,10.2],[7,33,18],[11,33,18.1],[2,33,22],[4,33,22.1]],[[9,33,3],[2,33,3.5],[2,33,4],[11,33,4.5],[4,33,5],[4,33,5.5],[5,33,6],[2,33,6.5],[11,33,7],[9,33,8]],[[6,33,0.5],[8,33,1],[2,33,1.5],[9,33,2],[5016,39,2.5]]]},{"ID":26,"towerID":606,"tjzdl":1000,"awardID":10026,"lvArr":[[[6,34,3],[2,34,3.1],[10,34,3.2],[8,34,10],[4,34,10.1],[5,34,10.2],[11,34,18],[10,34,18.1],[4,34,22],[3,34,22.1]],[[5,34,3],[3,34,3.1],[7,34,3.2],[6,34,10],[11,34,10.1],[9,34,10.2],[8,34,18],[4,34,18.1],[1,34,22],[10,34,22.1]]]},{"ID":27,"towerID":607,"tjzdl":1000,"awardID":10027,"lvArr":[[[8,35,3],[1,35,3.1],[1,35,3.2],[5,35,10],[2,35,10.1],[2,35,10.2],[8,35,18],[9,35,18.1],[1,35,22],[7,35,22.1]],[[10,35,3],[1,35,3.1],[9,35,3.2],[4,35,10],[6,35,10.1],[4,35,10.2],[8,35,18],[2,35,18.1],[2,35,22],[10,31,22.1]]]},{"ID":28,"towerID":608,"tjzdl":1000,"awardID":10028,"lvArr":[[[7,36,3],[2,36,3.1],[11,36,3.2],[8,36,10],[4,36,10.1],[9,36,10.2],[7,36,18],[11,36,18.1],[1,36,22],[1,36,22.1]],[[6,36,3],[6,36,3.1],[4,36,3.2],[8,36,10],[10,36,10.1],[11,36,10.2],[7,36,18],[2,36,18.1],[2,36,22],[4,32,22.1]]]},{"ID":29,"towerID":609,"tjzdl":1000,"awardID":10029,"lvArr":[[[9,37,3],[2,37,3.1],[10,37,3.2],[8,37,10],[4,37,10.1],[9,37,10.2],[7,37,18],[4,37,18.1],[1,37,22],[1,37,22.1]],[[6,37,3],[4,37,3.1],[5,37,3.2],[8,37,10],[10,37,10.1],[7,37,10.2],[7,37,18],[8,37,18.1],[2,37,22],[4,37,22.1]]]},{"ID":30,"towerID":610,"tjzdl":1000,"awardID":10030,"lvArr":[[[4,38,3],[2,38,3.1],[6,38,3.2],[11,38,10],[4,38,10.1],[9,38,10.2],[8,38,18],[10,38,18.1],[1,38,22],[1,38,22.1]],[[6,38,3],[7,38,3.1],[4,38,3.2],[5,38,10],[10,38,10.1],[6,38,10.2],[7,38,18],[10,38,18.1],[2,38,22],[4,38,22.1]],[[7,38,3],[2,38,3.5],[11,38,4],[8,38,4.5],[15,38,5],[9,38,5.5],[7,38,6],[11,38,6.5],[15,38,7],[15,38,8]],[[6,38,0.5],[6,38,1],[4,38,1.5],[8,38,2],[5013,44,2.5],[10,38,3],[7,38,3.5],[7,38,4],[2,38,4.5],[4,38,5]]]},{"ID":31,"towerID":701,"tjzdl":1000,"awardID":10031,"lvArr":[[[7,39,3],[2,39,3.1],[11,39,3.2],[8,39,10],[4,39,10.1],[9,39,10.2],[7,39,18],[11,39,18.1],[1,39,22],[1,39,22.1]],[[6,39,3],[6,39,3.1],[4,39,3.2],[8,39,10],[10,39,10.1],[11,39,10.2],[7,39,18],[2,39,18.1],[2,39,22],[4,39,22.1]]]},{"ID":32,"towerID":702,"tjzdl":1000,"awardID":10032,"lvArr":[[[5,40,3],[4,40,3.1],[8,40,3.2],[10,40,10],[4,40,10.1],[9,40,10.2],[6,40,18],[5,40,18.1],[2,40,22],[1,40,22.1]],[[3,40,3],[6,40,3.1],[4,40,3.2],[8,40,10],[10,40,10.1],[11,40,10.2],[7,40,18],[11,40,18.1],[2,40,22],[4,40,22.1]]]},{"ID":33,"towerID":703,"tjzdl":1000,"awardID":10033,"lvArr":[[[6,41,3],[3,41,3.1],[10,41,3.2],[8,41,10],[4,41,10.1],[9,41,10.2],[7,41,18],[5,41,18.1],[3,41,22],[1,41,22.1]],[[4,41,3],[5,41,3.1],[4,41,3.2],[7,41,10],[10,41,10.1],[8,41,10.2],[7,41,18],[7,41,18.1],[2,41,22],[4,41,22.1]]]},{"ID":34,"towerID":704,"tjzdl":1000,"awardID":10034,"lvArr":[[[6,42,3],[2,42,3.1],[10,42,3.2],[8,42,10],[4,42,10.1],[5,42,10.2],[11,42,18],[10,42,18.1],[4,42,22],[3,42,22.1]],[[5,42,3],[3,42,3.1],[7,42,3.2],[6,42,10],[11,42,10.1],[9,42,10.2],[8,42,18],[4,42,18.1],[1,42,22],[10,42,22.1]]]},{"ID":35,"towerID":705,"tjzdl":1000,"awardID":10035,"lvArr":[[[5,43,3],[4,43,3.1],[16,43,3.2],[10,43,10],[4,43,10.1],[9,43,10.2],[6,43,18],[5,43,18.1],[2,43,22],[1,43,22.1]],[[3,43,3],[6,43,3.1],[16,43,3.2],[8,43,10],[10,43,10.1],[11,43,10.2],[7,43,18],[2,43,18.1],[16,43,22],[4,43,22.1]],[[5,43,3],[14,43,3.5],[8,43,4],[10,43,4.5],[4,43,5],[9,43,5.5],[15,43,6],[17,43,6.5],[20,43,7],[9,43,8]],[[6,43,0.5],[9,43,1],[9,43,1.5],[10,43,2],[21,49,2.5]]]},{"ID":36,"towerID":706,"tjzdl":1000,"awardID":10036,"lvArr":[[[6,44,3],[2,44,3.1],[10,44,3.2],[8,44,10],[4,44,10.1],[5,44,10.2],[11,44,18],[10,44,18.1],[4,44,22],[3,44,22.1]],[[5,44,3],[3,44,3.1],[7,44,3.2],[6,44,10],[11,44,10.1],[9,44,10.2],[8,44,18],[4,44,18.1],[1,44,22],[10,44,22.1]]]},{"ID":37,"towerID":707,"tjzdl":1000,"awardID":10037,"lvArr":[[[8,45,3],[1,45,3.1],[1,45,3.2],[5,45,10],[2,45,10.1],[2,45,10.2],[8,45,18],[9,45,18.1],[1,45,22],[7,45,22.1]],[[10,45,3],[1,45,3.1],[9,45,3.2],[4,45,10],[6,45,10.1],[4,45,10.2],[8,45,18],[2,45,18.1],[2,45,22],[10,41,22.1]]]},{"ID":38,"towerID":708,"tjzdl":1000,"awardID":10038,"lvArr":[[[7,46,3],[2,46,3.1],[11,46,3.2],[8,46,10],[4,46,10.1],[9,46,10.2],[7,46,18],[11,46,18.1],[1,46,22],[1,46,22.1]],[[6,46,3],[6,46,3.1],[4,46,3.2],[8,46,10],[10,46,10.1],[11,46,10.2],[7,46,18],[11,46,18.1],[2,46,22],[4,42,22.1]]]},{"ID":39,"towerID":709,"tjzdl":1000,"awardID":10039,"lvArr":[[[9,47,3],[2,47,3.1],[10,47,3.2],[8,47,10],[4,47,10.1],[9,47,10.2],[7,47,18],[4,47,18.1],[1,47,22],[1,47,22.1]],[[6,47,3],[4,47,3.1],[5,47,3.2],[8,47,10],[10,47,10.1],[7,47,10.2],[7,47,18],[8,47,18.1],[2,47,22],[4,43,22.1]]]},{"ID":40,"towerID":710,"tjzdl":1000,"awardID":10040,"lvArr":[[[7,48,3],[9,48,3.1],[9,48,3.2],[9,48,10],[8,48,10.1],[8,48,10.2],[8,48,18],[10,48,18.1],[10,48,22],[10,48,22.1]],[[7,48,3],[8,48,3.1],[8,48,3.2],[11,48,10],[9,48,10.1],[9,48,10.2],[10,48,18],[10,48,18.1],[15,48,22],[15,44,22.1]],[[7,48,3],[15,48,3.5],[15,48,4],[9,48,4.5],[9,48,5],[10,48,5.5],[10,48,6],[10,48,6.5],[7,48,7],[8,48,8]],[[8,48,0.5],[8,48,1],[10,48,1.5],[10,48,2],[5022,54,2.5],[10,48,3],[7,48,3.5],[11,48,4],[9,48,4.5],[9,48,5]]]},{"ID":41,"towerID":801,"tjzdl":1000,"awardID":10041,"lvArr":[[[7,49,3],[2,49,3.1],[11,49,3.2],[8,49,10],[4,49,10.1],[9,49,10.2],[21,49,18],[11,49,18.1],[1,49,22],[1,49,22.1]],[[6,49,3],[6,49,3.1],[4,49,3.2],[8,49,10],[10,49,10.1],[11,49,10.2],[2,49,18],[2,49,18.1],[2,49,22],[4,49,22.1]]]},{"ID":42,"towerID":802,"tjzdl":1000,"awardID":10042,"lvArr":[[[7,50,3],[4,50,3.1],[8,50,3.2],[10,50,10],[4,50,10.1],[9,50,10.2],[6,50,18],[5,50,18.1],[2,50,22],[1,50,22.1]],[[3,50,3],[6,50,3.1],[4,50,3.2],[8,50,10],[10,50,10.1],[11,50,10.2],[21,50,18],[11,50,18.1],[2,50,22],[4,50,22.1]]]},{"ID":43,"towerID":803,"tjzdl":1000,"awardID":10043,"lvArr":[[[7,51,3],[3,51,3.1],[10,51,3.2],[8,51,10],[4,51,10.1],[9,51,10.2],[9,51,18],[5,51,18.1],[3,51,22],[1,51,22.1]],[[4,51,3],[5,51,3.1],[4,51,3.2],[21,51,10],[10,51,10.1],[8,51,10.2],[9,51,18],[8,51,18.1],[9,51,22],[9,51,22.1]]]},{"ID":44,"towerID":804,"tjzdl":1000,"awardID":10044,"lvArr":[[[7,52,3],[2,52,3.1],[10,52,3.2],[8,52,10],[4,52,10.1],[5,52,10.2],[11,52,18],[10,52,18.1],[4,52,22],[3,52,22.1]],[[5,52,3],[3,52,3.1],[21,52,3.2],[6,52,10],[11,52,10.1],[9,52,10.2],[8,52,18],[4,52,18.1],[1,52,22],[10,52,22.1]]]},{"ID":45,"towerID":805,"tjzdl":1000,"awardID":10045,"lvArr":[[[7,53,3],[4,53,3.1],[16,53,3.2],[10,53,10],[4,53,10.1],[9,53,10.2],[6,53,18],[5,53,18.1],[2,53,22],[1,53,22.1]],[[21,53,3],[6,53,3.1],[16,53,3.2],[8,53,10],[10,53,10.1],[11,53,10.2],[21,53,18],[2,53,18.1],[16,53,22],[4,53,22.1]],[[5,53,3],[14,53,3.5],[8,53,4],[10,53,4.5],[4,53,5],[9,53,5.5],[15,53,6],[17,53,6.5],[20,53,7],[9,53,8]],[[10,53,0.5],[9,53,1],[9,53,1.5],[5022,53,2]]]},{"ID":46,"towerID":806,"tjzdl":1000,"awardID":10046,"lvArr":[[[7,54,3],[2,54,3.1],[10,54,3.2],[8,54,10],[4,54,10.1],[5,54,10.2],[11,54,18],[10,54,18.1],[4,54,22],[3,54,22.1]],[[5,54,3],[3,54,3.1],[21,54,3.2],[6,54,10],[11,54,10.1],[9,54,10.2],[8,54,18],[4,54,18.1],[1,54,22],[10,54,22.1]]]},{"ID":47,"towerID":807,"tjzdl":1000,"awardID":10047,"lvArr":[[[21,55,3],[1,55,3.1],[1,55,3.2],[5,55,10],[2,55,10.1],[2,55,10.2],[8,55,18],[9,55,18.1],[1,55,22],[21,55,22.1]],[[10,55,3],[1,55,3.1],[9,55,3.2],[4,55,10],[6,55,10.1],[4,55,10.2],[8,55,18],[2,55,18.1],[2,55,22],[10,55,22.1]]]},{"ID":48,"towerID":808,"tjzdl":1000,"awardID":10048,"lvArr":[[[21,56,3],[2,56,3.1],[11,56,3.2],[8,56,10],[4,56,10.1],[9,56,10.2],[21,56,18],[11,56,18.1],[1,56,22],[1,56,22.1]],[[6,56,3],[6,56,3.1],[4,56,3.2],[8,56,10],[10,56,10.1],[17,56,10.2],[21,56,18],[17,56,18.1],[2,56,22],[4,56,22.1]]]},{"ID":49,"towerID":809,"tjzdl":1000,"awardID":10049,"lvArr":[[[9,57,3],[2,57,3.1],[10,57,3.2],[8,57,10],[4,57,10.1],[9,57,10.2],[7,57,18],[4,57,18.1],[1,57,22],[1,57,22.1]],[[6,57,3],[4,57,3.1],[5,57,3.2],[8,57,10],[10,57,10.1],[7,57,10.2],[7,57,18],[8,57,18.1],[2,57,22],[4,57,22.1]]]},{"ID":50,"towerID":810,"tjzdl":1000,"awardID":10050,"lvArr":[[[21,58,3],[19,58,3.1],[9,58,3.2],[9,58,10],[8,58,10.1],[8,58,10.2],[8,58,18],[10,58,18.1],[10,58,22],[19,58,22.1]],[[21,58,3],[8,58,3.1],[8,58,3.2],[11,58,10],[9,58,10.1],[9,58,10.2],[10,58,18],[10,58,18.1],[15,58,22],[15,58,22.1]],[[21,58,3],[15,58,3.5],[15,58,4],[9,58,4.5],[9,58,5],[10,58,5.5],[10,58,6],[10,58,6.5],[7,58,7],[8,58,8]],[[8,58,0.5],[8,58,1],[10,58,1.5],[10,58,2],[18,64,2.5],[10,58,3],[7,58,3.5],[11,58,4],[19,58,4.5],[19,58,5]]]},{"ID":51,"towerID":901,"tjzdl":1000,"awardID":10051,"lvArr":[[[4,59,3],[8,59,3.1],[2,59,3.2],[1,59,10],[7,59,10.1],[2,59,10.2],[9,59,18],[4,59,18.1],[1,59,22],[2,59,22.1]],[[5,59,3],[6,59,3.1],[6,59,3.2],[7,59,10],[1,59,10.1],[2,59,10.2],[9,59,18],[4,59,18.1],[7,59,22],[2,59,22.1]]]},{"ID":52,"towerID":902,"tjzdl":1000,"awardID":10052,"lvArr":[[[6,60,3],[2,60,3.1],[2,60,3.2],[7,60,10],[1,60,10.1],[9,60,10.2],[8,60,18],[4,60,18.1],[1,60,22],[2,60,22.1]],[[6,60,3],[6,60,3.1],[6,60,3.2],[8,60,10],[1,60,10.1],[2,60,10.2],[9,60,18],[4,60,18.1],[7,60,22],[2,60,22.1]]]},{"ID":53,"towerID":903,"tjzdl":1000,"awardID":10053,"lvArr":[[[8,61,3],[6,61,3.1],[10,61,3.2],[7,61,10],[1,61,10.1],[2,61,10.2],[8,61,18],[4,61,18.1],[4,61,22],[7,61,22.1]],[[9,61,3],[2,61,3.1],[2,61,3.2],[6,61,10],[4,61,10.1],[4,61,10.2],[5,61,18],[2,61,18.1],[10,61,22],[9,61,22.1]]]},{"ID":54,"towerID":904,"tjzdl":1000,"awardID":10054,"lvArr":[[[6,62,3],[7,62,3.1],[2,62,3.2],[9,62,10],[8,62,10.1],[2,62,10.2],[2,62,18],[6,62,18.1],[4,62,22],[4,62,22.1]],[[9,62,3],[2,62,3.1],[2,62,3.2],[6,62,10],[4,62,10.1],[4,62,10.2],[5,62,18],[2,62,18.1],[10,62,22],[9,62,22.1]]]},{"ID":55,"towerID":905,"tjzdl":1000,"awardID":10055,"lvArr":[[[8,63,3],[2,63,3.1],[1,63,3.2],[7,63,10],[2,63,10.1],[6,63,10.2],[8,63,18],[6,63,18.1],[1,63,22],[6,63,22.1]],[[6,63,3],[7,63,3.1],[2,63,3.2],[9,63,10],[8,63,10.1],[2,63,10.2],[2,63,18],[6,63,18.1],[4,63,22],[4,63,22.1]],[[9,63,3],[2,63,3.5],[2,63,4],[11,63,4.5],[4,63,5],[4,63,5.5],[5,63,6],[2,63,6.5],[11,63,7],[9,63,8]],[[6,63,0.5],[8,63,1],[2,63,1.5],[9,63,2],[14,20,2.5]]]},{"ID":56,"towerID":906,"tjzdl":1000,"awardID":10056,"lvArr":[[[7,64,3],[16,64,3.1],[11,64,3.2],[8,64,10],[4,64,10.1],[9,64,10.2],[7,64,18],[16,64,18.1],[1,64,22],[1,64,22.1]],[[6,64,3],[6,64,3.1],[17,64,3.2],[8,64,10],[10,64,10.1],[11,64,10.2],[7,64,18],[17,64,18.1],[2,64,22],[4,64,22.1]]]},{"ID":57,"towerID":907,"tjzdl":1000,"awardID":10057,"lvArr":[[[9,65,3],[2,65,3.1],[10,65,3.2],[8,65,10],[4,65,10.1],[9,65,10.2],[7,65,18],[4,65,18.1],[11,65,22],[1,65,22.1]],[[6,65,3],[4,65,3.1],[17,65,3.2],[8,65,10],[10,65,10.1],[7,65,10.2],[17,65,18],[8,65,18.1],[2,65,22],[4,65,22.1]]]},{"ID":58,"towerID":908,"tjzdl":1000,"awardID":10058,"lvArr":[[[7,66,3],[16,66,3.1],[11,66,3.2],[8,66,10],[4,66,10.1],[9,66,10.2],[7,66,18],[16,66,18.1],[1,66,22],[1,66,22.1]],[[6,66,3],[6,66,3.1],[17,66,3.2],[8,66,10],[10,66,10.1],[11,66,10.2],[7,66,18],[17,66,18.1],[2,66,22],[4,66,22.1]]]},{"ID":59,"towerID":909,"tjzdl":1000,"awardID":10059,"lvArr":[[[9,67,3],[2,67,3.1],[10,67,3.2],[8,67,10],[4,67,10.1],[9,67,10.2],[7,67,18],[4,67,18.1],[11,67,22],[1,67,22.1]],[[6,67,3],[4,67,3.1],[17,67,3.2],[8,67,10],[10,67,10.1],[7,67,10.2],[17,67,18],[8,67,18.1],[2,67,22],[4,67,22.1]]]},{"ID":60,"towerID":910,"tjzdl":1000,"awardID":10060,"lvArr":[[[5,68,3],[4,68,3.1],[8,68,3.2],[10,68,10],[17,68,10.1],[9,68,10.2],[11,68,18],[5,68,18.1],[2,68,22],[1,68,22.1]],[[9,68,3],[2,68,3.1],[10,68,3.2],[8,68,10],[4,68,10.1],[9,68,10.2],[7,68,18],[4,68,18.1],[11,68,22],[1,68,22.1]],[[6,68,3],[4,68,3.5],[17,68,4],[8,68,4.5],[10,68,5],[7,68,5.5],[17,68,6],[8,68,6.5],[2,68,7],[4,68,8]],[[19,68,0.5],[11,68,1],[13,68,1.5],[13,68,2],[6,25,2.5],[13,68,3],[10,68,3.5],[17,68,4],[10,68,4.5],[10,68,5]]]},{"ID":61,"towerID":1001,"tjzdl":1000,"awardID":10061,"lvArr":[[[6,69,3],[3,69,3.1],[10,69,3.2],[8,69,10],[4,69,10.1],[9,69,10.2],[7,69,18],[5,69,18.1],[3,69,22],[1,69,22.1]],[[4,69,3],[5,69,3.1],[4,69,3.2],[7,69,10],[10,69,10.1],[8,69,10.2],[7,69,18],[7,69,18.1],[2,69,22],[4,69,22.1]]]},{"ID":62,"towerID":1002,"tjzdl":1000,"awardID":10062,"lvArr":[[[8,70,3],[1,70,3.1],[1,70,3.2],[5,70,10],[2,70,10.1],[2,70,10.2],[8,70,18],[9,70,18.1],[1,70,22],[7,70,22.1]],[[10,70,3],[1,70,3.1],[9,70,3.2],[4,70,10],[6,70,10.1],[4,70,10.2],[8,70,18],[2,70,18.1],[2,70,22],[10,70,22.1]]]},{"ID":63,"towerID":1003,"tjzdl":1000,"awardID":10063,"lvArr":[[[6,71,3],[2,71,3.1],[10,71,3.2],[8,71,10],[4,71,10.1],[5,71,10.2],[11,71,18],[10,71,18.1],[4,71,22],[3,71,22.1]],[[5,71,3],[3,71,3.1],[7,71,3.2],[6,71,10],[11,71,10.1],[9,71,10.2],[8,71,18],[4,71,18.1],[1,71,22],[10,71,22.1]]]},{"ID":64,"towerID":1004,"tjzdl":1000,"awardID":10064,"lvArr":[[[8,72,3],[7,72,3.1],[5,72,3.2],[4,72,10],[3,72,10.1],[10,72,10.2],[5,72,18],[3,72,18.1],[1,72,22],[9,72,22.1]],[[5,72,3],[3,72,3.1],[7,72,3.2],[5,72,10],[7,72,10.1],[9,72,10.2],[11,72,18],[10,72,18.1],[4,72,22],[3,72,22.1]]]},{"ID":65,"towerID":1005,"tjzdl":1000,"awardID":10065,"lvArr":[[[8,73,3],[2,73,3.1],[1,73,3.2],[7,73,10],[2,73,10.1],[6,73,10.2],[8,73,18],[6,73,18.1],[12,73,22],[2,73,22.1]],[[6,73,3],[7,73,3.1],[2,73,3.2],[9,73,10],[8,73,10.1],[2,73,10.2],[2,73,18],[6,73,18.1],[2,73,22],[2,73,22.1]],[[9,73,3],[2,73,3.5],[2,73,4],[11,73,4.5],[4,73,5],[4,73,5.5],[5,73,6],[2,73,6.5],[11,73,7],[9,73,8]],[[6,73,0.5],[8,73,1],[2,73,1.5],[9,73,2],[21,30,2.5]]]},{"ID":66,"towerID":1006,"tjzdl":1000,"awardID":10066,"lvArr":[[[3,74,3],[2,74,3.1],[10,74,3.2],[9,74,10],[7,74,10.1],[11,74,10.2],[10,74,18],[9,74,18.1],[3,74,22],[1,74,22.1]],[[9,74,3],[1,74,3.1],[4,74,3.2],[8,74,10],[9,74,10.1],[10,74,10.2],[7,74,18],[11,74,18.1],[2,74,22],[4,74,22.1]]]},{"ID":67,"towerID":1007,"tjzdl":1000,"awardID":10067,"lvArr":[[[5,75,3],[2,75,3.1],[6,75,3.2],[10,75,10],[9,75,10.1],[11,75,10.2],[6,75,18],[5,75,18.1],[2,75,22],[1,75,22.1]],[[7,75,3],[6,75,3.1],[4,75,3.2],[8,75,10],[10,75,10.1],[5,75,10.2],[7,75,18],[11,75,18.1],[2,75,22],[4,75,22.1]]]},{"ID":68,"towerID":1008,"tjzdl":1000,"awardID":10068,"lvArr":[[[6,76,3],[3,76,3.1],[10,76,3.2],[8,76,10],[4,76,10.1],[9,76,10.2],[7,76,18],[5,76,18.1],[3,76,22],[1,76,22.1]],[[4,76,3],[5,76,3.1],[4,76,3.2],[7,76,10],[10,76,10.1],[8,76,10.2],[7,76,18],[7,76,18.1],[2,76,22],[4,76,22.1]]]},{"ID":69,"towerID":1009,"tjzdl":1000,"awardID":10069,"lvArr":[[[7,77,3],[2,77,3.1],[11,77,3.2],[8,77,10],[10,77,10.1],[8,77,10.2],[7,77,18],[4,77,18.1],[1,77,22],[1,77,22.1]],[[6,77,3],[5,77,3.1],[4,77,3.2],[8,77,10],[10,77,10.1],[6,77,10.2],[7,77,18],[11,77,18.1],[2,77,22],[4,77,22.1]]]},{"ID":70,"towerID":1010,"tjzdl":1000,"awardID":10070,"lvArr":[[[8,78,3],[2,78,3.1],[1,78,3.2],[7,78,10],[2,78,10.1],[6,78,10.2],[8,78,18],[6,78,18.1],[12,78,22],[2,78,22.1]],[[6,78,3],[7,78,3.1],[2,78,3.2],[9,78,10],[8,78,10.1],[2,78,10.2],[2,78,18],[6,78,18.1],[2,78,22],[2,78,22.1]],[[12,78,3],[2,78,3.5],[2,78,4],[17,78,4.5],[4,78,5],[12,78,5.5],[15,78,6],[2,78,6.5],[17,78,7],[9,78,8]],[[9,78,0.5],[2,78,1],[2,78,1.5],[17,78,2],[19,35,2.5],[4,78,3],[15,78,3.5],[2,78,4],[17,78,4.5],[9,78,5]]]},{"ID":71,"towerID":1101,"tjzdl":1000,"awardID":10071,"lvArr":[[[8,79,3],[2,79,3.1],[1,79,3.2],[7,79,10],[2,79,10.1],[6,79,10.2],[8,79,18],[6,79,18.1],[12,79,22],[2,79,22.1]],[[6,79,3],[7,79,3.1],[2,79,3.2],[9,79,10],[8,79,10.1],[2,79,10.2],[2,79,18],[6,79,18.1],[2,79,22],[2,79,22.1]]]},{"ID":72,"towerID":1102,"tjzdl":1000,"awardID":10072,"lvArr":[[[6,80,3],[3,80,3.1],[10,80,3.2],[8,80,10],[4,80,10.1],[9,80,10.2],[7,80,18],[5,80,18.1],[3,80,22],[1,80,22.1]],[[4,80,3],[5,80,3.1],[4,80,3.2],[7,80,10],[10,80,10.1],[8,80,10.2],[7,80,18],[7,80,18.1],[2,80,22],[4,80,22.1]]]},{"ID":73,"towerID":1103,"tjzdl":1000,"awardID":10073,"lvArr":[[[8,81,3],[1,81,3.1],[1,81,3.2],[5,81,10],[2,81,10.1],[2,81,10.2],[8,81,18],[9,81,18.1],[1,81,22],[7,81,22.1]],[[10,81,3],[1,81,3.1],[9,81,3.2],[4,81,10],[6,81,10.1],[4,81,10.2],[8,81,18],[2,81,18.1],[2,81,22],[10,81,22.1]]]},{"ID":74,"towerID":1104,"tjzdl":1000,"awardID":10074,"lvArr":[[[6,82,3],[2,82,3.1],[10,82,3.2],[8,82,10],[4,82,10.1],[5,82,10.2],[11,82,18],[10,82,18.1],[4,82,22],[3,82,22.1]],[[5,82,3],[3,82,3.1],[7,82,3.2],[6,82,10],[11,82,10.1],[9,82,10.2],[8,82,18],[4,82,18.1],[1,82,22],[10,82,22.1]]]},{"ID":75,"towerID":1105,"tjzdl":1000,"awardID":10075,"lvArr":[[[5,83,3],[4,83,3.1],[8,83,3.2],[10,83,10],[4,83,10.1],[9,83,10.2],[6,83,18],[5,83,18.1],[2,83,22],[1,83,22.1]],[[3,83,3],[6,83,3.1],[4,83,3.2],[8,83,10],[10,83,10.1],[11,83,10.2],[7,83,18],[11,83,18.1],[2,83,22],[4,83,22.1]],[[9,83,3],[2,83,3.5],[2,83,4],[11,83,4.5],[4,83,5],[4,83,5.5],[5,83,6],[2,83,6.5],[11,83,7],[9,83,8]],[[6,83,0.5],[8,83,1],[2,83,1.5],[9,83,2],[16,39,2.5]]]},{"ID":76,"towerID":1106,"tjzdl":1000,"awardID":10076,"lvArr":[[[6,84,3],[2,84,3.1],[10,84,3.2],[8,84,10],[4,84,10.1],[5,84,10.2],[11,84,18],[10,84,18.1],[4,84,22],[3,84,22.1]],[[5,84,3],[3,84,3.1],[7,84,3.2],[6,84,10],[11,84,10.1],[9,84,10.2],[8,84,18],[4,84,18.1],[1,84,22],[10,84,22.1]]]},{"ID":77,"towerID":1107,"tjzdl":1000,"awardID":10077,"lvArr":[[[8,85,3],[1,85,3.1],[1,85,3.2],[5,85,10],[2,85,10.1],[2,85,10.2],[8,85,18],[9,85,18.1],[1,85,22],[7,85,22.1]],[[10,85,3],[1,85,3.1],[9,85,3.2],[4,85,10],[6,85,10.1],[4,85,10.2],[8,85,18],[2,85,18.1],[2,85,22],[10,85,22.1]]]},{"ID":78,"towerID":1108,"tjzdl":1000,"awardID":10078,"lvArr":[[[7,86,3],[2,86,3.1],[11,86,3.2],[8,86,10],[4,86,10.1],[9,86,10.2],[7,86,18],[11,86,18.1],[1,86,22],[1,86,22.1]],[[6,86,3],[6,86,3.1],[4,86,3.2],[8,86,10],[10,86,10.1],[11,86,10.2],[7,86,18],[2,86,18.1],[2,86,22],[4,86,22.1]]]},{"ID":79,"towerID":1109,"tjzdl":1000,"awardID":10079,"lvArr":[[[9,87,3],[2,87,3.1],[10,87,3.2],[8,87,10],[4,87,10.1],[9,87,10.2],[7,87,18],[4,87,18.1],[1,87,22],[1,87,22.1]],[[6,87,3],[4,87,3.1],[5,87,3.2],[8,87,10],[10,87,10.1],[7,87,10.2],[7,87,18],[8,87,18.1],[2,87,22],[4,87,22.1]]]},{"ID":80,"towerID":1110,"tjzdl":1000,"awardID":10080,"lvArr":[[[4,88,3],[2,88,3.1],[6,88,3.2],[11,88,10],[4,88,10.1],[9,88,10.2],[8,88,18],[10,88,18.1],[1,88,22],[1,88,22.1]],[[6,88,3],[7,88,3.1],[4,88,3.2],[5,88,10],[10,88,10.1],[6,88,10.2],[7,88,18],[10,88,18.1],[2,88,22],[4,88,22.1]],[[7,88,3],[2,88,3.5],[11,88,4],[8,88,4.5],[15,88,5],[9,88,5.5],[7,88,6],[11,88,6.5],[15,88,7],[15,88,8]],[[6,88,0.5],[6,88,1],[4,88,1.5],[8,88,2],[13,44,2.5],[10,88,3],[7,88,3.5],[7,88,4],[2,88,4.5],[4,88,5]]]},{"ID":81,"towerID":1201,"tjzdl":1000,"awardID":10081,"lvArr":[[[7,89,3],[2,89,3.1],[11,89,3.2],[8,89,10],[4,89,10.1],[9,89,10.2],[7,89,18],[11,89,18.1],[1,89,22],[1,89,22.1]],[[6,89,3],[6,89,3.1],[4,89,3.2],[8,89,10],[10,89,10.1],[11,89,10.2],[7,89,18],[2,89,18.1],[2,89,22],[4,89,22.1]]]},{"ID":82,"towerID":1202,"tjzdl":1000,"awardID":10082,"lvArr":[[[5,90,3],[4,90,3.1],[8,90,3.2],[10,90,10],[4,90,10.1],[9,90,10.2],[6,90,18],[5,90,18.1],[2,90,22],[1,90,22.1]],[[3,90,3],[6,90,3.1],[4,90,3.2],[8,90,10],[10,90,10.1],[11,90,10.2],[7,90,18],[11,90,18.1],[2,90,22],[4,90,22.1]]]},{"ID":83,"towerID":1203,"tjzdl":1000,"awardID":10083,"lvArr":[[[6,91,3],[3,91,3.1],[10,91,3.2],[8,91,10],[4,91,10.1],[9,91,10.2],[7,91,18],[5,91,18.1],[3,91,22],[1,91,22.1]],[[4,91,3],[5,91,3.1],[4,91,3.2],[7,91,10],[10,91,10.1],[8,91,10.2],[7,91,18],[7,91,18.1],[2,91,22],[4,91,22.1]]]},{"ID":84,"towerID":1204,"tjzdl":1000,"awardID":10084,"lvArr":[[[6,92,3],[2,92,3.1],[10,92,3.2],[8,92,10],[4,92,10.1],[5,92,10.2],[11,92,18],[10,92,18.1],[4,92,22],[3,92,22.1]],[[5,92,3],[3,92,3.1],[7,92,3.2],[6,92,10],[11,92,10.1],[9,92,10.2],[8,92,18],[4,92,18.1],[1,92,22],[10,92,22.1]]]},{"ID":85,"towerID":1205,"tjzdl":1000,"awardID":10085,"lvArr":[[[5,93,3],[4,93,3.1],[16,93,3.2],[10,93,10],[4,93,10.1],[9,93,10.2],[6,93,18],[5,93,18.1],[2,93,22],[1,93,22.1]],[[3,93,3],[6,93,3.1],[16,93,3.2],[8,93,10],[10,93,10.1],[11,93,10.2],[7,93,18],[2,93,18.1],[16,93,22],[4,93,22.1]],[[5,93,3],[14,93,3.5],[8,93,4],[10,93,4.5],[4,93,5],[9,93,5.5],[15,93,6],[17,93,6.5],[20,93,7],[9,93,8]],[[10,93,0.5],[9,93,1],[9,93,1.5],[21,93,2]]]},{"ID":86,"towerID":1206,"tjzdl":1000,"awardID":10086,"lvArr":[[[6,94,3],[2,94,3.1],[10,94,3.2],[8,94,10],[4,94,10.1],[5,94,10.2],[11,94,18],[10,94,18.1],[4,94,22],[3,94,22.1]],[[5,94,3],[3,94,3.1],[7,94,3.2],[6,94,10],[11,94,10.1],[9,94,10.2],[8,94,18],[4,94,18.1],[1,94,22],[10,94,22.1]]]},{"ID":87,"towerID":1207,"tjzdl":1000,"awardID":10087,"lvArr":[[[8,95,3],[1,95,3.1],[1,95,3.2],[5,95,10],[2,95,10.1],[2,95,10.2],[8,95,18],[9,95,18.1],[1,95,22],[7,95,22.1]],[[10,95,3],[1,95,3.1],[9,95,3.2],[4,95,10],[6,95,10.1],[4,95,10.2],[8,95,18],[2,95,18.1],[2,95,22],[10,95,22.1]]]},{"ID":88,"towerID":1208,"tjzdl":1000,"awardID":10088,"lvArr":[[[7,96,3],[2,96,3.1],[11,96,3.2],[8,96,10],[4,96,10.1],[9,96,10.2],[7,96,18],[11,96,18.1],[1,96,22],[1,96,22.1]],[[6,96,3],[6,96,3.1],[4,96,3.2],[8,96,10],[10,96,10.1],[11,96,10.2],[7,96,18],[11,96,18.1],[2,96,22],[4,96,22.1]]]},{"ID":89,"towerID":1209,"tjzdl":1000,"awardID":10089,"lvArr":[[[9,97,3],[2,97,3.1],[10,97,3.2],[8,97,10],[4,97,10.1],[9,97,10.2],[7,97,18],[4,97,18.1],[1,97,22],[1,97,22.1]],[[6,97,3],[4,97,3.1],[5,97,3.2],[8,97,10],[10,97,10.1],[7,97,10.2],[7,97,18],[8,97,18.1],[2,97,22],[4,97,22.1]]]},{"ID":90,"towerID":1210,"tjzdl":1000,"awardID":10090,"lvArr":[[[7,48,3],[9,48,3.1],[9,48,3.2],[9,48,10],[8,48,10.1],[8,48,10.2],[8,48,18],[10,48,18.1],[10,48,22],[10,48,22.1]],[[7,48,3],[8,48,3.1],[8,48,3.2],[11,48,10],[9,48,10.1],[9,48,10.2],[10,48,18],[10,48,18.1],[15,48,22],[15,44,22.1]],[[7,48,3],[15,48,3.5],[15,48,4],[9,48,4.5],[9,48,5],[10,48,5.5],[10,48,6],[10,48,6.5],[7,48,7],[8,48,8]],[[8,48,0.5],[8,48,1],[10,48,1.5],[10,48,2],[22,54,2.5],[11,48,3],[7,48,3.5],[11,48,4],[9,48,4.5],[9,48,5]]]},{"ID":91,"towerID":1301,"tjzdl":1000,"awardID":10091,"lvArr":[[[7,49,3],[2,49,3.1],[11,49,3.2],[8,49,10],[4,49,10.1],[9,49,10.2],[21,49,18],[11,49,18.1],[1,49,22],[1,49,22.1]],[[6,49,3],[6,49,3.1],[4,49,3.2],[8,49,10],[10,49,10.1],[11,49,10.2],[2,49,18],[2,49,18.1],[2,49,22],[4,49,22.1]]]},{"ID":92,"towerID":1302,"tjzdl":1000,"awardID":10092,"lvArr":[[[7,50,3],[4,50,3.1],[8,50,3.2],[10,50,10],[4,50,10.1],[9,50,10.2],[6,50,18],[5,50,18.1],[2,50,22],[1,50,22.1]],[[3,50,3],[6,50,3.1],[4,50,3.2],[8,50,10],[10,50,10.1],[11,50,10.2],[21,50,18],[11,50,18.1],[2,50,22],[4,50,22.1]]]},{"ID":93,"towerID":1303,"tjzdl":1000,"awardID":10093,"lvArr":[[[7,51,3],[3,51,3.1],[10,51,3.2],[8,51,10],[4,51,10.1],[9,51,10.2],[9,51,18],[5,51,18.1],[3,51,22],[1,51,22.1]],[[4,51,3],[5,51,3.1],[4,51,3.2],[21,51,10],[10,51,10.1],[8,51,10.2],[9,51,18],[8,51,18.1],[9,51,22],[9,51,22.1]]]},{"ID":94,"towerID":1304,"tjzdl":1000,"awardID":10094,"lvArr":[[[7,52,3],[2,52,3.1],[10,52,3.2],[8,52,10],[4,52,10.1],[5,52,10.2],[11,52,18],[10,52,18.1],[4,52,22],[3,52,22.1]],[[5,52,3],[3,52,3.1],[21,52,3.2],[6,52,10],[11,52,10.1],[9,52,10.2],[8,52,18],[4,52,18.1],[1,52,22],[10,52,22.1]]]},{"ID":95,"towerID":1305,"tjzdl":1000,"awardID":10095,"lvArr":[[[5,53,3],[14,53,3.5],[8,53,4],[10,53,4.5],[4,53,5],[9,53,5.5],[15,53,6],[17,53,6.5],[20,53,7],[9,53,8]],[[14,53,0.5],[9,53,1],[9,53,1.5],[10,53,2],[22,49,2.5]]]},{"ID":96,"towerID":1306,"tjzdl":1000,"awardID":10096,"lvArr":[[[7,54,3],[2,54,3.1],[10,54,3.2],[8,54,10],[4,54,10.1],[5,54,10.2],[11,54,18],[10,54,18.1],[4,54,22],[3,54,22.1]],[[5,54,3],[3,54,3.1],[21,54,3.2],[6,54,10],[11,54,10.1],[9,54,10.2],[8,54,18],[4,54,18.1],[1,54,22],[10,54,22.1]]]},{"ID":97,"towerID":1307,"tjzdl":1000,"awardID":10097,"lvArr":[[[21,55,3],[1,55,3.1],[1,55,3.2],[5,55,10],[2,55,10.1],[2,55,10.2],[8,55,18],[9,55,18.1],[1,55,22],[21,55,22.1]],[[10,55,3],[1,55,3.1],[9,55,3.2],[4,55,10],[6,55,10.1],[4,55,10.2],[8,55,18],[2,55,18.1],[2,55,22],[10,55,22.1]]]},{"ID":98,"towerID":1308,"tjzdl":1000,"awardID":10098,"lvArr":[[[21,56,3],[2,56,3.1],[11,56,3.2],[8,56,10],[4,56,10.1],[9,56,10.2],[21,56,18],[11,56,18.1],[1,56,22],[1,56,22.1]],[[6,56,3],[6,56,3.1],[4,56,3.2],[8,56,10],[10,56,10.1],[17,56,10.2],[21,56,18],[17,56,18.1],[2,56,22],[4,56,22.1]]]},{"ID":99,"towerID":1309,"tjzdl":1000,"awardID":10099,"lvArr":[[[9,57,3],[2,57,3.1],[10,57,3.2],[8,57,10],[4,57,10.1],[9,57,10.2],[7,57,18],[4,57,18.1],[1,57,22],[1,57,22.1]],[[6,57,3],[4,57,3.1],[5,57,3.2],[8,57,10],[10,57,10.1],[7,57,10.2],[7,57,18],[8,57,18.1],[2,57,22],[4,57,22.1]]]},{"ID":100,"towerID":1310,"tjzdl":1000,"awardID":10100,"lvArr":[[[21,58,3],[19,58,3.1],[9,58,3.2],[9,58,10],[8,58,10.1],[8,58,10.2],[8,58,18],[10,58,18.1],[10,58,22],[19,58,22.1]],[[21,58,3],[8,58,3.1],[8,58,3.2],[11,58,10],[9,58,10.1],[9,58,10.2],[10,58,18],[10,58,18.1],[15,58,22],[15,58,22.1]],[[21,58,3],[15,58,3.5],[15,58,4],[9,58,4.5],[9,58,5],[10,58,5.5],[10,58,6],[10,58,6.5],[7,58,7],[8,58,8]],[[8,58,0.5],[8,58,1],[10,58,1.5],[11,58,2],[18,64,2.5],[9,58,3],[7,58,3.5],[11,58,4],[19,58,4.5],[19,58,5]]]}]}]],0,0,[],[],[]]